client/api.py
client/client.py
tokapi_client-0.0.2.dist-info/LICENSE
tokapi_client-0.0.2.dist-info/METADATA
tokapi_client-0.0.2.dist-info/WHEEL
tokapi_client-0.0.2.dist-info/top_level.txt
tokapi_client-0.0.2.dist-info/RECORD
