Metadata-Version: 2.1
Name: tokapi-client
Version: 0.0.2
Summary: Simple http client for TokApi rapid-api tiktok mobile API
Home-page: https://github.com/mtokapi/tokapi-client
Author: Somjik
License: MIT
Platform: UNKNOWN
Classifier: Programming Language :: Python :: 3
Classifier: License :: OSI Approved :: MIT License
Classifier: Operating System :: OS Independent
Requires-Python: >=3.6
Requires-Dist: httpx
